pynascar/__init__.py
pynascar/caching.py
pynascar/codes.py
pynascar/config.py
pynascar/definitions.py
pynascar/driver.py
pynascar/init.py
pynascar/race.py
pynascar/schedule.py
pynascar/test_driver.py
pynascar/utils.py
pynascar/core/base_api.py
pynascar/core/process_data.py
pynascar/data_classes/race_models.py
pynascar-0.2.1.dist-info/licenses/LICENSE
pynascar-0.2.1.dist-info/METADATA
pynascar-0.2.1.dist-info/WHEEL
pynascar-0.2.1.dist-info/top_level.txt
pynascar-0.2.1.dist-info/RECORD
