Metadata-Version: 2.4
Name: pynascar
Version: 0.2.1
Summary: Unofficial tools for NASCAR data
Author-email: ab5525 <admin@jakbytes.com>
License: MIT
Project-URL: Homepage, https://github.com/ab5525/pynascar
Project-URL: Repository, https://github.com/ab5525/pynascar
Project-URL: Issues, https://github.com/ab5525/pynascar/issues
Keywords: nascar,motorsport,data,api
Classifier: Programming Language :: Python :: 3
Classifier: License :: OSI Approved :: MIT License
Classifier: Operating System :: OS Independent
Requires-Python: >=3.9
License-File: LICENSE
Requires-Dist: ipykernel>=6.29.5
Requires-Dist: numpy<2.3,>=1.26
Requires-Dist: pandas>=2.3.1
Requires-Dist: pyarrow>=21.0.0
Requires-Dist: requests>=2.32.4
Requires-Dist: seaborn>=0.13.2
Requires-Dist: tabulate>=0.9.0
Provides-Extra: cache
Requires-Dist: pyarrow>=16.1.0; extra == "cache"
Dynamic: license-file
